ourtils/__init__.py
ourtils/diffs.py
ourtils/excel.py
ourtils/general.py
ourtils/managers.py
ourtils/misc.py
ourtils/modeling.py
ourtils/visualize.py
ourtils/wrangling.py
ourtils-1.0.2.dist-info/LICENSE
ourtils-1.0.2.dist-info/METADATA
ourtils-1.0.2.dist-info/WHEEL
ourtils-1.0.2.dist-info/RECORD
