Metadata-Version: 2.3
Name: ourtils
Version: 1.0.2
Summary: Useful code for working with data.
Author: Anthony
Author-email: anthony.yoskovich@gmail.com
Requires-Python: >=3.10
Classifier: Programming Language :: Python :: 3
Classifier: Programming Language :: Python :: 3.10
Classifier: Programming Language :: Python :: 3.11
Classifier: Programming Language :: Python :: 3.12
Classifier: Programming Language :: Python :: 3.13
Requires-Dist: black (>=25.1.0)
Requires-Dist: matplotlib (>=3.10.1,<4.0.0)
Requires-Dist: pandas (>=2.2.3,<3.0.0)
Requires-Dist: plotly (>=6.0.1,<7.0.0)
Requires-Dist: pytest (>=8.4.1)
Requires-Dist: pytest-coverage (>=0.0)
Requires-Dist: ruff (>=0.12.1)
Requires-Dist: scikit-learn (==1.6.1)
Requires-Dist: scipy (<=1.15.3)
Requires-Dist: seaborn (>=0.13.2)
Requires-Dist: spacy (>=3.8.7)
Requires-Dist: statsmodels (>=0.14.4,<0.15.0)
